vectrs/.DS_Store
vectrs/__init__.py
vectrs/load_balancer.py
vectrs/main.py
vectrs/replication_manager.py
vectrs/config/config_utils.py
vectrs/database/.DS_Store
vectrs/database/__init__.py
vectrs/database/filter.py
vectrs/database/util.py
vectrs/database/vectrbase.py
vectrs/database/__pycache__/__init__.cpython-38.pyc
vectrs/database/__pycache__/filter.cpython-38.pyc
vectrs/database/__pycache__/util.cpython-38.pyc
vectrs/database/__pycache__/vectrbase.cpython-38.pyc
vectrs/network/.DS_Store
vectrs/network/__init__.py
vectrs/network/kademlia_node.py
vectrs/network/node.py
vectrs/network/__pycache__/__init__.cpython-38.pyc
vectrs/network/__pycache__/node.cpython-38.pyc
vectrs/networking/message_broker.py
vectrs/swarms/__init__.py
vectrs/swarms/agent_factory.py
vectrs/swarms/main.py
vectrs/swarms/types.py
vectrs/swarms/agents/base_agent.py
vectrs/swarms/agents/generation_agent.py
vectrs/swarms/agents/planning_agent.py
vectrs/swarms/agents/reflection_agent.py
vectrs/swarms/agents/retrieval_agent.py
vectrs/swarms/agents/tool_agent.py
vectrs/swarms/coordinator/multi_agent_coordinator.py
vectrs/swarms/knowledge_base/vector_db.py
vectrs/swarms/llm/anthropic_llm.py
vectrs/swarms/llm/llm_interface.py
vectrs/swarms/utils/error_handler.py
vectrs/swarms/utils/task_analyzer.py
vectrs/utils/error_handler.py
vectrs/utils/task_analyzer.py
vectrs-0.3.3.dist-info/LICENSE
vectrs-0.3.3.dist-info/METADATA
vectrs-0.3.3.dist-info/WHEEL
vectrs-0.3.3.dist-info/top_level.txt
vectrs-0.3.3.dist-info/RECORD
