Metadata-Version: 2.1
Name: vectrs
Version: 0.3.3
Summary: Decentralized & Distributed Vector Database
Home-page: https://github.com/ParalexLabs/Vectrs-beta
Author: Mir Sakib
Author-email: sakib@paralex.tech
Classifier: Programming Language :: Python :: 3
Classifier: License :: OSI Approved :: Apache Software License
Classifier: Operating System :: OS Independent
Requires-Python: >=3.8
License-File: LICENSE
Requires-Dist: numpy
Requires-Dist: kademlia
Requires-Dist: networkx
Requires-Dist: anthropic
Requires-Dist: sentence-transformers
Requires-Dist: hnswlib
Requires-Dist: scipy
